merlin/__init__.py
merlin_quandela-0.0.1.dist-info/METADATA
merlin_quandela-0.0.1.dist-info/WHEEL
merlin_quandela-0.0.1.dist-info/top_level.txt
merlin_quandela-0.0.1.dist-info/RECORD
