Metadata-Version: 2.4
Name: merlin-quandela
Version: 0.0.1
Summary: Coming soon
Author-email: quandela <perceval@quandela.com>
